{
  "project_info": {
    "project_number": "72397033455",
    "firebase_url": "https://messenger-app-58dce.firebaseio.com",
    "project_id": "messenger-app-58dce",
    "storage_bucket": "messenger-app-58dce.appspot.com"
  },
  "client": [
    {
      "client_info": {
        "mobilesdk_app_id": "1:72397033455:android:b5c44b139b462113",
        "android_client_info": {
          "package_name": "com.maxiarce.radoommessenger"
        }
      },
      "oauth_client": [
        {
          "client_id": "72397033455-ltcr2nfuc4f52fp2uc33iget9v3s88ai.apps.googleusercontent.com",
          "client_type": 3
        }
      ],
      "api_key": [
        {
          "current_key": "AIzaSyAl351E60yZV-vNeAkV1K57GIoWbDiS_b0"
        }
      ],
      "services": {
        "analytics_service": {
          "status": 1
        },
        "appinvite_service": {
          "status": 1,
          "other_platform_oauth_client": []
        },
        "ads_service": {
          "status": 2
        }
      }
    }
  ],
  "configuration_version": "1"
}